sigils_fastapi/__init__.py
sigils_fastapi/__main__.py
sigils_fastapi/redirect.py
sigils_fastapi-0.1.0.dist-info/METADATA
sigils_fastapi-0.1.0.dist-info/WHEEL
sigils_fastapi-0.1.0.dist-info/top_level.txt
sigils_fastapi-0.1.0.dist-info/RECORD
