Metadata-Version: 2.1
Name: sigils-fastapi
Version: 0.1.0
Summary: Example [[SIGILS]] server with FastAPI.
Author-email: Rafael Jesús Guillén Osorio <arthexis@gmail.com>
Project-URL: Source, https://github.com/arthexis/sigils
Project-URL: Bug-Tracker, https://github.com/arthexis/sigils/issues
Keywords: utils,sigils,string,text,magic,context
Classifier: Development Status :: 3 - Alpha
Classifier: Intended Audience :: Developers
Classifier: Topic :: Internet :: WWW/HTTP :: Dynamic Content
Classifier: Environment :: Console
Classifier: License :: OSI Approved :: MIT License
Classifier: Programming Language :: Python :: 3
Classifier: Programming Language :: Python :: 3.10
Classifier: Programming Language :: Python :: 3.11
Requires-Python: >=3.9
Requires-Dist: sigils (>=0.2.1)
Requires-Dist: FastAPI (>=0.92.0)
Provides-Extra: dev
Requires-Dist: pytest ; extra == 'dev'
